django_prod/__init__.py
django_prod/apps.py
django_prod/management/__init__.py
django_prod/management/commands/__init__.py
django_prod/management/commands/django_prod_deploy.py
django_prod/management/commands/django_prod_init.py
django_prod/templates/boilerplate/.env.prod.txt
django_prod/templates/boilerplate/docker-compose.yaml.txt
django_prod/templates/boilerplate/entrypoint.prod.sh.txt
django_prod/templates/boilerplate/prod.Dockerfile.txt
django_prod/templates/boilerplate/settings_prod.py.txt
django_prod-0.1.2.dist-info/METADATA
django_prod-0.1.2.dist-info/WHEEL
django_prod-0.1.2.dist-info/entry_points.txt
django_prod-0.1.2.dist-info/RECORD
