Metadata-Version: 2.4
Name: django-prod
Version: 0.1.2
Summary: Add your description here
Author-email: MayasNova <code@mayasnova.com>
Requires-Python: >=3.12
Requires-Dist: django>=4.2
Requires-Dist: gunicorn>=23.0.0
Requires-Dist: python-dotenv>=1.1.0
Requires-Dist: questionary>=2.1.0
Requires-Dist: scp>=0.15.0
Requires-Dist: whitenoise>=6.9.0
